condastats/__init__.py
condastats/_version.py
condastats/cli.py
condastats/condastats.py
condastats-0.2.1.dist-info/LICENSE
condastats-0.2.1.dist-info/METADATA
condastats-0.2.1.dist-info/WHEEL
condastats-0.2.1.dist-info/entry_points.txt
condastats-0.2.1.dist-info/top_level.txt
condastats-0.2.1.dist-info/RECORD
