Metadata-Version: 2.1
Name: condastats
Version: 0.2.1
Summary: Conda package stats CLI
Home-page: https://github.com/sophiamyang/condastats
Author: Sophia Man Yang
Author-email: UNKNOWN
License: BSD license
Keywords: condastats
Platform: UNKNOWN
Classifier: Development Status :: 2 - Pre-Alpha
Classifier: Intended Audience :: Developers
Classifier: License :: OSI Approved :: BSD License
Classifier: Natural Language :: English
Classifier: Programming Language :: Python :: 3
Classifier: Programming Language :: Python :: 3.7
Classifier: Programming Language :: Python :: 3.8
Classifier: Programming Language :: Python :: 3.9
Classifier: Programming Language :: Python :: 3.10
Requires-Dist: numpy (>=1.16.5)
Requires-Dist: dask[dataframe]
Requires-Dist: pyarrow
Requires-Dist: s3fs
Requires-Dist: python-snappy
